bleedml/__init__.py
bleedml/classifiers.py
bleedml/utils.py
bleedml-0.0.7.dist-info/DESCRIPTION.rst
bleedml-0.0.7.dist-info/METADATA
bleedml-0.0.7.dist-info/RECORD
bleedml-0.0.7.dist-info/WHEEL
bleedml-0.0.7.dist-info/metadata.json
bleedml-0.0.7.dist-info/top_level.txt
