Metadata-Version: 2.0
Name: bleedml
Version: 0.0.7
Summary: Bleeding edge Machine Learning Algorithms
Home-page: http://github.com/sig-ml/bleedml
Author: Arjoonn Sharma
Author-email: arjoonn.94@gmail.com
License: MIT
Platform: UNKNOWN
Requires-Dist: numpy
Requires-Dist: scipy
Requires-Dist: sklearn
